[
    {
        "id":0,
        "number":"1",
        "titleFalam":"KUM THAR THU",
        "titleEnglish":"(New Year)",
        "filePath":"data/pdf/1. PATHIAN SUNGLAWI SIN SEH.pdf",
        "favorite":false
    },
    {
        "id":1,
        "number":"2",
        "titleFalam":"PATHIAN IH UMPINAK",
        "titleEnglish":"(God’s Presence)",
        "filePath":"data/pdf/2. DAWTNAK BAWI KA TUUKHAL ASI.pdf",
        "favorite":false
    },
    {
        "id":2,
        "number":"3",
        "titleFalam":"SIRNAK IN PATHIAN BETU PAWL",
        "titleEnglish":"(Contrite Worshippers)",
        "filePath":"data/pdf/3. SIANGPAHRANG BIA UH.pdf",
        "favorite":true
    },
    {
        "id":3,
        "number":"4",
        "titleFalam":"PATHIAN INN",
        "titleEnglish":"Zaanlam",
        "filePath":"data/pdf/4. KAN SIANGPAHRANG THANGQHAT SINSIN UH.pdf",
        "favorite":false
    },
    {
        "id":4,
        "number":"5",
        "titleFalam":"UNAU HRINKHAT FA SINAK",
        "titleEnglish":"(Race Relations)",
        "filePath":"data/pdf/5. PATHIAN KAN THANGTHAT.pdf",
        "favorite":true
    }


]